astrodeb/__init__.py
astrodeb/deblur.py
astrodeb-0.1.2.dist-info/licenses/LICENSE
astrodeb-0.1.2.dist-info/METADATA
astrodeb-0.1.2.dist-info/WHEEL
astrodeb-0.1.2.dist-info/top_level.txt
astrodeb-0.1.2.dist-info/RECORD
