Metadata-Version: 2.4
Name: astrodeb
Version: 0.1.2
Summary: Deblur astronomical images using Richardson-Lucy deconvolution and wavelet denoising.
Home-page: https://github.com/atharvaansingkar/Image-Deblurring
Author: SASA
Author-email: sasa.flux@gmail.com
Classifier: Programming Language :: Python :: 3
Classifier: License :: OSI Approved :: MIT License
Classifier: Operating System :: OS Independent
Requires-Python: >=3.7
License-File: LICENSE
Requires-Dist: numpy
Requires-Dist: Pillow
Requires-Dist: scikit-image
Dynamic: author
Dynamic: author-email
Dynamic: classifier
Dynamic: description
Dynamic: description-content-type
Dynamic: home-page
Dynamic: license-file
Dynamic: requires-dist
Dynamic: requires-python
Dynamic: summary
